<annotation>
	<folder>my-project-name</folder>
	<filename>20201106_224520.jpg</filename>
	<path>/my-project-name/20201106_224520.jpg</path>
	<source>
		<database>Unspecified</database>
	</source>
	<size>
		<width>259</width>
		<height>59</height>
		<depth>3</depth>
	</size>
	<object>
		<name>4</name>
		<pose>Unspecified</pose>
		<truncated>Unspecified</truncated>
		<difficult>Unspecified</difficult>
		<bndbox>
			<xmin>18</xmin>
			<ymin>10</ymin>
			<xmax>37</xmax>
			<ymax>50</ymax>
		</bndbox>
	</object>
	<object>
		<name>9</name>
		<pose>Unspecified</pose>
		<truncated>Unspecified</truncated>
		<difficult>Unspecified</difficult>
		<bndbox>
			<xmin>38</xmin>
			<ymin>12</ymin>
			<xmax>56</xmax>
			<ymax>50</ymax>
		</bndbox>
	</object>
	<object>
		<name>7</name>
		<pose>Unspecified</pose>
		<truncated>Unspecified</truncated>
		<difficult>Unspecified</difficult>
		<bndbox>
			<xmin>58</xmin>
			<ymin>11</ymin>
			<xmax>76</xmax>
			<ymax>51</ymax>
		</bndbox>
	</object>
	<object>
		<name>9</name>
		<pose>Unspecified</pose>
		<truncated>Unspecified</truncated>
		<difficult>Unspecified</difficult>
		<bndbox>
			<xmin>78</xmin>
			<ymin>12</ymin>
			<xmax>96</xmax>
			<ymax>50</ymax>
		</bndbox>
	</object>
	<object>
		<name>3</name>
		<pose>Unspecified</pose>
		<truncated>Unspecified</truncated>
		<difficult>Unspecified</difficult>
		<bndbox>
			<xmin>98</xmin>
			<ymin>12</ymin>
			<xmax>116</xmax>
			<ymax>51</ymax>
		</bndbox>
	</object>
	<object>
		<name>h</name>
		<pose>Unspecified</pose>
		<truncated>Unspecified</truncated>
		<difficult>Unspecified</difficult>
		<bndbox>
			<xmin>166</xmin>
			<ymin>21</ymin>
			<xmax>188</xmax>
			<ymax>45</ymax>
		</bndbox>
	</object>
	<object>
		<name>6</name>
		<pose>Unspecified</pose>
		<truncated>Unspecified</truncated>
		<difficult>Unspecified</difficult>
		<bndbox>
			<xmin>228</xmin>
			<ymin>14</ymin>
			<xmax>246</xmax>
			<ymax>54</ymax>
		</bndbox>
	</object>
</annotation>